anyvar/__init__.py
anyvar/anyvar.py
anyvar/extras/__init__.py
anyvar/extras/vcf.py
anyvar/queueing/__init__.py
anyvar/queueing/celery_worker.py
anyvar/restapi/__init__.py
anyvar/restapi/auth.py
anyvar/restapi/main.py
anyvar/restapi/schema.py
anyvar/restapi/vcf.py
anyvar/storage/__init__.py
anyvar/storage/base_storage.py
anyvar/storage/mapper_registry.py
anyvar/storage/mappers.py
anyvar/storage/no_db.py
anyvar/storage/orm.py
anyvar/storage/postgres.py
anyvar/storage/snowflake.py
anyvar/translate/__init__.py
anyvar/translate/translate.py
anyvar/translate/vrs_python.py
anyvar/utils/__init__.py
anyvar/utils/funcs.py
anyvar/utils/liftover_utils.py
anyvar/utils/types.py
biocommons_anyvar-1.0.0rc3.dist-info/licenses/LICENSE
biocommons_anyvar-1.0.0rc3.dist-info/METADATA
biocommons_anyvar-1.0.0rc3.dist-info/WHEEL
biocommons_anyvar-1.0.0rc3.dist-info/top_level.txt
biocommons_anyvar-1.0.0rc3.dist-info/RECORD
