Metadata-Version: 2.4
Name: biocommons.anyvar
Version: 1.0.0rc3
Summary: AnyVar provides Python and REST interfaces to validate, normalize, generate identifiers, and register biological sequence variation according to the GA4GH Variation Representation standards.
Author-email: biocommons contributors <biocommons-dev@googlegroups.com>
License:                                  Apache License
Project-URL: Homepage, https://github.com/biocommons/anyvar
Project-URL: Documentation, https://github.com/biocommons/anyvar/
Project-URL: Changelog, https://github.com/biocommons/anyvar/releases
Project-URL: Source, https://github.com/biocommons/anyvar/
Project-URL: Bug Tracker, https://github.com/biocommons/anyvar/issues
Classifier: Programming Language :: Python :: 3
Classifier: Programming Language :: Python :: 3.11
Classifier: Programming Language :: Python :: 3.12
Classifier: Programming Language :: Python :: 3.13
Classifier: Programming Language :: Python :: 3.14
Classifier: License :: OSI Approved :: MIT License
Classifier: Operating System :: OS Independent
Requires-Python: >=3.11
License-File: LICENSE
Requires-Dist: fastapi>=0.95.0
Requires-Dist: python-multipart
Requires-Dist: uvicorn
Requires-Dist: ga4gh.vrs[extras]<3.0,>=2.2.0
Requires-Dist: sqlalchemy~=2.0.0
Requires-Dist: snowflake-sqlalchemy~=1.8.2
Requires-Dist: pyyaml
Requires-Dist: agct>=0.2.0rc1
Requires-Dist: pysam
Requires-Dist: python-dotenv
Requires-Dist: anyio
Requires-Dist: bioutils
Provides-Extra: postgres
Requires-Dist: psycopg[binary]; extra == "postgres"
Provides-Extra: queueing
Requires-Dist: celery[redis]~=5.5.0; extra == "queueing"
Requires-Dist: aiofiles; extra == "queueing"
Provides-Extra: test
Requires-Dist: pytest; extra == "test"
Requires-Dist: pytest-asyncio; extra == "test"
Requires-Dist: pytest-cov; extra == "test"
Requires-Dist: pytest-mock; extra == "test"
Requires-Dist: httpx; extra == "test"
Requires-Dist: celery[pytest]; extra == "test"
Requires-Dist: jsonschema; extra == "test"
Requires-Dist: pyyaml; extra == "test"
Provides-Extra: dev
Requires-Dist: ruff==0.12.8; extra == "dev"
Requires-Dist: pre-commit>=4.2.0; extra == "dev"
Requires-Dist: ipykernel; extra == "dev"
Provides-Extra: docs
Requires-Dist: sphinx==8.2.3; extra == "docs"
Requires-Dist: sphinx_rtd_theme==3.0.2; extra == "docs"
Requires-Dist: sphinx-autodoc-typehints==3.2.0; extra == "docs"
Requires-Dist: sphinx-autobuild==2024.10.3; extra == "docs"
Requires-Dist: sphinx-copybutton==0.5.2; extra == "docs"
Requires-Dist: sphinxext-opengraph==0.10.0; extra == "docs"
Requires-Dist: sphinx-github-changelog==1.7.1; extra == "docs"
Dynamic: license-file
